botup/__init__.py
botup/api.py
botup/bot.py
botup/dispatcher.py
botup/exceptions.py
botup/handlers.py
botup/navigation.py
botup/types.py
botup/utils.py
botup/widget.py
botup/constants/__init__.py
botup/constants/api_method.py
botup/constants/base.py
botup/constants/bot_command_scope_type.py
botup/constants/chat_action.py
botup/constants/chat_member_status.py
botup/constants/chat_type.py
botup/constants/encrypted_passport_element_type.py
botup/constants/inline_query_chat_type.py
botup/constants/inline_query_result_type.py
botup/constants/input_file_type.py
botup/constants/input_media_type.py
botup/constants/mask_position_point.py
botup/constants/menu_button_type.py
botup/constants/message_entity_type.py
botup/constants/passport_element_error_source.py
botup/constants/poll_type.py
botup/constants/sticker_type.py
botup/constants/update_type.py
botup/mixins/__init__.py
botup/mixins/echo.py
botup/state_manager/__init__.py
botup/state_manager/base.py
botup/state_manager/redis.py
botup/widgets/__init__.py
botup/widgets/date_picker.py
tests/__init__.py
tests/conftest.py
tests/test_dispatcher.py
tests/test_dispatcher_decorator.py
tests/test_serializing.py
tests/utils.py
telegram_botup-1.0.6.dist-info/METADATA
telegram_botup-1.0.6.dist-info/WHEEL
telegram_botup-1.0.6.dist-info/top_level.txt
telegram_botup-1.0.6.dist-info/RECORD
