Metadata-Version: 2.1
Name: telegram-botup
Version: 1.0.6
Summary: Python library for building Telegram bots
Home-page: UNKNOWN
Author: Dmitry Shebotinov
Author-email: groovestreetmagic@gmail.com
License: UNKNOWN
Project-URL: Source Code, https://github.com/spirtum/telegram-botup
Platform: UNKNOWN
Classifier: License :: OSI Approved :: Python Software Foundation License
Requires-Python: >=3.8
Requires-Dist: aiohttp
Provides-Extra: redis
Requires-Dist: redis ; extra == 'redis'
